{
  "document_tone": {
    "tone_categories": [
      {
        "category_id": "emotion_tone",
        "category_name": "Emotion Tone",
        "tones": [
          {
            "tone_id": "anger",
            "tone_name": "Anger",
            "score": 0.261754
          },
          {
            "tone_id": "disgust",
            "tone_name": "Disgust",
            "score": 0.095586
          },
          {
            "tone_id": "fear",
            "tone_name": "Fear",
            "score": 0.236624
          },
          {
            "tone_id": "joy",
            "tone_name": "Joy",
            "score": 0.008928
          },
          {
            "tone_id": "sadness",
            "tone_name": "Sadness",
            "score": 0.558815
          }
        ]
      },
      {
        "category_id": "language_tone",
        "category_name": "Language Tone",
        "tones": [
          {
            "tone_id": "analytical",
            "tone_name": "Analytical",
            "score": 0.671097
          },
          {
            "tone_id": "confident",
            "tone_name": "Confident",
            "score": 0.6697
          },
          {
            "tone_id": "tentative",
            "tone_name": "Tentative",
            "score": 0.0
          }
        ]
      },
      {
        "category_id": "social_tone",
        "category_name": "Social Tone",
        "tones": [
          {
            "tone_id": "openness_big5",
            "tone_name": "Openness",
            "score": 0.339087
          },
          {
            "tone_id": "conscientiousness_big5",
            "tone_name": "Conscientiousness",
            "score": 0.002823
          },
          {
            "tone_id": "extraversion_big5",
            "tone_name": "Extraversion",
            "score": 0.002459
          },
          {
            "tone_id": "agreeableness_big5",
            "tone_name": "Agreeableness",
            "score": 9.8E-5
          },
          {
            "tone_id": "emotional_range_big5",
            "tone_name": "Emotional Range",
            "score": 0.689572
          }
        ]
      }
    ]
  },
  "sentences_tone": [
    {
      "sentence_id": 0,
      "input_from": 0,
      "input_to": 87,
      "text": "I running an exe from a .NET app and trying to redirect standard out to a streamreader.",
      "tone_categories": [
        {
          "category_id": "emotion_tone",
          "category_name": "Emotion Tone",
          "tones": [
            {
              "tone_id": "anger",
              "tone_name": "Anger",
              "score": 0.35571
            },
            {
              "tone_id": "disgust",
              "tone_name": "Disgust",
              "score": 0.068358
            },
            {
              "tone_id": "fear",
              "tone_name": "Fear",
              "score": 0.137827
            },
            {
              "tone_id": "joy",
              "tone_name": "Joy",
              "score": 0.074726
            },
            {
              "tone_id": "sadness",
              "tone_name": "Sadness",
              "score": 0.449228
            }
          ]
        },
        {
          "category_id": "language_tone",
          "category_name": "Language Tone",
          "tones": [
            {
              "tone_id": "analytical",
              "tone_name": "Analytical",
              "score": 0.698634
            },
            {
              "tone_id": "confident",
              "tone_name": "Confident",
              "score": 0.0
            },
            {
              "tone_id": "tentative",
              "tone_name": "Tentative",
              "score": 0.26216
            }
          ]
        },
        {
          "category_id": "social_tone",
          "category_name": "Social Tone",
          "tones": [
            {
              "tone_id": "openness_big5",
              "tone_name": "Openness",
              "score": 0.179789
            },
            {
              "tone_id": "conscientiousness_big5",
              "tone_name": "Conscientiousness",
              "score": 0.039197
            },
            {
              "tone_id": "extraversion_big5",
              "tone_name": "Extraversion",
              "score": 0.172906
            },
            {
              "tone_id": "agreeableness_big5",
              "tone_name": "Agreeableness",
              "score": 0.008191
            },
            {
              "tone_id": "emotional_range_big5",
              "tone_name": "Emotional Range",
              "score": 0.655608
            }
          ]
        }
      ]
    },
    {
      "sentence_id": 1,
      "input_from": 88,
      "input_to": 131,
      "text": "The problem is that when I do myprocess.exe",
      "tone_categories": [
        {
          "category_id": "emotion_tone",
          "category_name": "Emotion Tone",
          "tones": [
            {
              "tone_id": "anger",
              "tone_name": "Anger",
              "score": 0.13724
            },
            {
              "tone_id": "disgust",
              "tone_name": "Disgust",
              "score": 0.282208
            },
            {
              "tone_id": "fear",
              "tone_name": "Fear",
              "score": 0.129998
            },
            {
              "tone_id": "joy",
              "tone_name": "Joy",
              "score": 0.047602
            },
            {
              "tone_id": "sadness",
              "tone_name": "Sadness",
              "score": 0.516025
            }
          ]
        },
        {
          "category_id": "language_tone",
          "category_name": "Language Tone",
          "tones": [
            {
              "tone_id": "analytical",
              "tone_name": "Analytical",
              "score": 0.724236
            },
            {
              "tone_id": "confident",
              "tone_name": "Confident",
              "score": 0.0
            },
            {
              "tone_id": "tentative",
              "tone_name": "Tentative",
              "score": 0.0
            }
          ]
        },
        {
          "category_id": "social_tone",
          "category_name": "Social Tone",
          "tones": [
            {
              "tone_id": "openness_big5",
              "tone_name": "Openness",
              "score": 0.623371
            },
            {
              "tone_id": "conscientiousness_big5",
              "tone_name": "Conscientiousness",
              "score": 0.118554
            },
            {
              "tone_id": "extraversion_big5",
              "tone_name": "Extraversion",
              "score": 0.103343
            },
            {
              "tone_id": "agreeableness_big5",
              "tone_name": "Agreeableness",
              "score": 0.022572
            },
            {
              "tone_id": "emotional_range_big5",
              "tone_name": "Emotional Range",
              "score": 0.741449
            }
          ]
        }
      ]
    },
    {
      "sentence_id": 2,
      "input_from": 132,
      "input_to": 142,
      "text": "\u003e\u003e out.txt",
      "tone_categories": [
        {
          "category_id": "emotion_tone",
          "category_name": "Emotion Tone",
          "tones": [
            {
              "tone_id": "anger",
              "tone_name": "Anger",
              "score": 0.112937
            },
            {
              "tone_id": "disgust",
              "tone_name": "Disgust",
              "score": 0.066285
            },
            {
              "tone_id": "fear",
              "tone_name": "Fear",
              "score": 0.236049
            },
            {
              "tone_id": "joy",
              "tone_name": "Joy",
              "score": 0.350003
            },
            {
              "tone_id": "sadness",
              "tone_name": "Sadness",
              "score": 0.307493
            }
          ]
        },
        {
          "category_id": "language_tone",
          "category_name": "Language Tone",
          "tones": [
            {
              "tone_id": "analytical",
              "tone_name": "Analytical",
              "score": 0.0
            },
            {
              "tone_id": "confident",
              "tone_name": "Confident",
              "score": 0.0
            },
            {
              "tone_id": "tentative",
              "tone_name": "Tentative",
              "score": 0.0
            }
          ]
        },
        {
          "category_id": "social_tone",
          "category_name": "Social Tone",
          "tones": [
            {
              "tone_id": "openness_big5",
              "tone_name": "Openness",
              "score": 0.259481
            },
            {
              "tone_id": "conscientiousness_big5",
              "tone_name": "Conscientiousness",
              "score": 0.274635
            },
            {
              "tone_id": "extraversion_big5",
              "tone_name": "Extraversion",
              "score": 0.544053
            },
            {
              "tone_id": "agreeableness_big5",
              "tone_name": "Agreeableness",
              "score": 0.599086
            },
            {
              "tone_id": "emotional_range_big5",
              "tone_name": "Emotional Range",
              "score": 0.285203
            }
          ]
        }
      ]
    },
    {
      "sentence_id": 3,
      "input_from": 143,
      "input_to": 168,
      "text": "out.txt is close to 14mb.",
      "tone_categories": [
        {
          "category_id": "emotion_tone",
          "category_name": "Emotion Tone",
          "tones": [
            {
              "tone_id": "anger",
              "tone_name": "Anger",
              "score": 0.228835
            },
            {
              "tone_id": "disgust",
              "tone_name": "Disgust",
              "score": 0.02948
            },
            {
              "tone_id": "fear",
              "tone_name": "Fear",
              "score": 0.273466
            },
            {
              "tone_id": "joy",
              "tone_name": "Joy",
              "score": 0.305095
            },
            {
              "tone_id": "sadness",
              "tone_name": "Sadness",
              "score": 0.240991
            }
          ]
        },
        {
          "category_id": "language_tone",
          "category_name": "Language Tone",
          "tones": [
            {
              "tone_id": "analytical",
              "tone_name": "Analytical",
              "score": 0.0
            },
            {
              "tone_id": "confident",
              "tone_name": "Confident",
              "score": 0.0
            },
            {
              "tone_id": "tentative",
              "tone_name": "Tentative",
              "score": 0.0
            }
          ]
        },
        {
          "category_id": "social_tone",
          "category_name": "Social Tone",
          "tones": [
            {
              "tone_id": "openness_big5",
              "tone_name": "Openness",
              "score": 0.097504
            },
            {
              "tone_id": "conscientiousness_big5",
              "tone_name": "Conscientiousness",
              "score": 0.267049
            },
            {
              "tone_id": "extraversion_big5",
              "tone_name": "Extraversion",
              "score": 0.379761
            },
            {
              "tone_id": "agreeableness_big5",
              "tone_name": "Agreeableness",
              "score": 0.592219
            },
            {
              "tone_id": "emotional_range_big5",
              "tone_name": "Emotional Range",
              "score": 0.469559
            }
          ]
        }
      ]
    },
    {
      "sentence_id": 4,
      "input_from": 169,
      "input_to": 360,
      "text": "When I do the command line version it is very fast but when I run the process from my csharp app it is excruciatingly slow because I believe the default streamreader flushes every 4096 bytes.",
      "tone_categories": [
        {
          "category_id": "emotion_tone",
          "category_name": "Emotion Tone",
          "tones": [
            {
              "tone_id": "anger",
              "tone_name": "Anger",
              "score": 0.204458
            },
            {
              "tone_id": "disgust",
              "tone_name": "Disgust",
              "score": 0.104446
            },
            {
              "tone_id": "fear",
              "tone_name": "Fear",
              "score": 0.192823
            },
            {
              "tone_id": "joy",
              "tone_name": "Joy",
              "score": 0.034836
            },
            {
              "tone_id": "sadness",
              "tone_name": "Sadness",
              "score": 0.578372
            }
          ]
        },
        {
          "category_id": "language_tone",
          "category_name": "Language Tone",
          "tones": [
            {
              "tone_id": "analytical",
              "tone_name": "Analytical",
              "score": 0.383036
            },
            {
              "tone_id": "confident",
              "tone_name": "Confident",
              "score": 0.575269
            },
            {
              "tone_id": "tentative",
              "tone_name": "Tentative",
              "score": 0.0
            }
          ]
        },
        {
          "category_id": "social_tone",
          "category_name": "Social Tone",
          "tones": [
            {
              "tone_id": "openness_big5",
              "tone_name": "Openness",
              "score": 0.380089
            },
            {
              "tone_id": "conscientiousness_big5",
              "tone_name": "Conscientiousness",
              "score": 0.001604
            },
            {
              "tone_id": "extraversion_big5",
              "tone_name": "Extraversion",
              "score": 4.16E-4
            },
            {
              "tone_id": "agreeableness_big5",
              "tone_name": "Agreeableness",
              "score": 0.0
            },
            {
              "tone_id": "emotional_range_big5",
              "tone_name": "Emotional Range",
              "score": 0.541043
            }
          ]
        }
      ]
    },
    {
      "sentence_id": 5,
      "input_from": 361,
      "input_to": 435,
      "text": "Is there a way to change the default stream reader for the Process object?",
      "tone_categories": [
        {
          "category_id": "emotion_tone",
          "category_name": "Emotion Tone",
          "tones": [
            {
              "tone_id": "anger",
              "tone_name": "Anger",
              "score": 0.123766
            },
            {
              "tone_id": "disgust",
              "tone_name": "Disgust",
              "score": 0.177014
            },
            {
              "tone_id": "fear",
              "tone_name": "Fear",
              "score": 0.166919
            },
            {
              "tone_id": "joy",
              "tone_name": "Joy",
              "score": 0.168263
            },
            {
              "tone_id": "sadness",
              "tone_name": "Sadness",
              "score": 0.472494
            }
          ]
        },
        {
          "category_id": "language_tone",
          "category_name": "Language Tone",
          "tones": [
            {
              "tone_id": "analytical",
              "tone_name": "Analytical",
              "score": 0.358523
            },
            {
              "tone_id": "confident",
              "tone_name": "Confident",
              "score": 0.0
            },
            {
              "tone_id": "tentative",
              "tone_name": "Tentative",
              "score": 0.0
            }
          ]
        },
        {
          "category_id": "social_tone",
          "category_name": "Social Tone",
          "tones": [
            {
              "tone_id": "openness_big5",
              "tone_name": "Openness",
              "score": 0.662946
            },
            {
              "tone_id": "conscientiousness_big5",
              "tone_name": "Conscientiousness",
              "score": 0.161969
            },
            {
              "tone_id": "extraversion_big5",
              "tone_name": "Extraversion",
              "score": 0.088719
            },
            {
              "tone_id": "agreeableness_big5",
              "tone_name": "Agreeableness",
              "score": 0.018288
            },
            {
              "tone_id": "emotional_range_big5",
              "tone_name": "Emotional Range",
              "score": 0.853555
            }
          ]
        }
      ]
    }
  ]
}